Metadata-Version: 2.4
Name: llama-index-readers-feishu-docs
Version: 0.4.1
Summary: llama-index readers feishu_docs integration
Author-email: Your Name <you@example.com>
Maintainer: ma-chengcheng
License-Expression: MIT
License-File: LICENSE
Requires-Python: <4.0,>=3.9
Requires-Dist: llama-index-core<0.15,>=0.13.0
Requires-Dist: requests<3,>=2.31.0
